natten/_C.cpython-39-x86_64-linux-gnu.so
natten/__init__.py
natten/flops.py
natten/functional.py
natten/nattencuda.py
natten/nattencuda1d.py
natten/nattencuda2d.py
natten-0.14.1.dist-info/LICENSE
natten-0.14.1.dist-info/METADATA
natten-0.14.1.dist-info/WHEEL
natten-0.14.1.dist-info/top_level.txt
natten-0.14.1.dist-info/RECORD
